docker_launch/__init__.py
docker_launch/config_parser.py
docker_launch/connection.py
docker_launch/console/__init__.py
docker_launch/console/check_command.py
docker_launch/console/up_command.py
docker_launch/exceptions.py
docker_launch/launch.py
docker_launch/ssh.py
docker_launch/typing.py
docker_launch/utils.py
docker_launch-0.2.2.dist-info/entry_points.txt
docker_launch-0.2.2.dist-info/LICENSE
docker_launch-0.2.2.dist-info/WHEEL
docker_launch-0.2.2.dist-info/METADATA
docker_launch-0.2.2.dist-info/RECORD
