Metadata-Version: 2.1
Name: docker-launch
Version: 0.2.2
Summary: Create and launch docker containers on multiple hosts.
Home-page: https://github.com/necst-telescope/docker-launch
License: MIT
Author: KaoruNishikawa
Author-email: k.nishikawa@a.phys.nagoya-u.ac.jp
Requires-Python: >=3.6,<4.0
Classifier: License :: OSI Approved :: MIT License
Classifier: Programming Language :: Python :: 3
Classifier: Programming Language :: Python :: 3.6
Classifier: Programming Language :: Python :: 3.7
Classifier: Programming Language :: Python :: 3.8
Classifier: Programming Language :: Python :: 3.9
Classifier: Programming Language :: Python :: 3.10
Requires-Dist: cleo (>=0.8.1,<0.9.0)
Requires-Dist: docker (>=5.0.3,<6.0.0)
Requires-Dist: importlib-metadata (>=4.4,<5.0); python_version < "3.8"
Requires-Dist: paramiko (>=2.11.0,<3.0.0)
Requires-Dist: tomlkit (>=0.11.1,<0.12.0)
Requires-Dist: typing-extensions (>=4.1,<5.0); python_version < "3.8"
Project-URL: Repository, https://github.com/necst-telescope/docker-launch
